monailisa/__init__.py
monailisa/subject.py
monailisa-0.1.13.dist-info/METADATA
monailisa-0.1.13.dist-info/WHEEL
monailisa-0.1.13.dist-info/entry_points.txt
monailisa-0.1.13.dist-info/RECORD
